wayfair_api_client/__init__.py
wayfair_api_client/client.py
wayfair_api_client/queries.py
wayfair_api_client/utils.py
wayfair_api_client-0.0.14.dist-info/METADATA
wayfair_api_client-0.0.14.dist-info/WHEEL
wayfair_api_client-0.0.14.dist-info/top_level.txt
wayfair_api_client-0.0.14.dist-info/RECORD
